bcligpt/__init__.py
bcligpt/app.py
bcligpt-2.0.0.dist-info/METADATA
bcligpt-2.0.0.dist-info/WHEEL
bcligpt-2.0.0.dist-info/entry_points.txt
bcligpt-2.0.0.dist-info/top_level.txt
bcligpt-2.0.0.dist-info/RECORD
