Metadata-Version: 2.1
Name: bcligpt
Version: 2.0.0
Summary: Better CLI for GPT
Author-email: Marco Filippozzi <marco.filippozzi98@gmail.com>
Requires-Dist: openai
Requires-Dist: tiktoken
Requires-Dist: rich
